[
   {
      "name":"SingStar Like All Editions for Start Singing Great Songs",
      "url":"https://ultrastarplay.github.io/AllEditions.zip",
      "description":"Songs Collection from various artists like SingStar was with their Editions. ≈ 318 songs, 1.5 MB"
   },
   {
      "name":"All Songs of USDB - 26800 Songs for Singing Forever and ever",
      "url":"https://github.com/UltraStarPlay/USPS/raw/refs/heads/main/All.zip",
      "description":"The USDB Songs Collection All Songs with: ≈ 26800 songs, 75 MB"
   },
   {
      "name":"All Songs of USDB Part 1 0-9 and A-F - 26800 Songs for Singing Forever and ever",
      "url":"https://ultrastarplay.github.io/AllAF.zip",
      "description":"Part 1 0-9 and A-F - The USDB Songs Collection with: ≈ 9000 songs, 25 MB"
   },
   {
      "name":"All Songs of USDB Part 2 G-O - 26800 Songs for Singing Forever and ever",
      "url":"https://ultrastarplay.github.io/AllGO.zip",
      "description":"Part 2 G-O - The USDB Songs Collection with: ≈ 8500 songs, 25 MB"
   },
   {
      "name":"All Songs of USDB Part 3 P-Z and more - 26800 Songs for Singing Forever and ever",
      "url":"https://ultrastarplay.github.io/AllPZ.zip",
      "description":"Part 3 P-Z and more - The USDB Songs Collection with: ≈ 8400 songs, 25 MB"
   },
   {
      "name":"UltraStar-Deluxe CC Songs",
      "url":"https://github.com/UltraStar-Deluxe/songs/archive/refs/heads/master.zip",
      "description":"Creative Commons licensed songs from various artists. ≈ 40 songs, 300 MB"
   }
]
